{
    "Version": "1.1",
    "Data": {
        "Source": "c:\\workspace\\sideproject1\\engine\\intermediate\\build\\win64\\x64\\unrealeditor\\development\\webbrowser\\module.webbrowser.cpp",
        "ProvidedModule": "",
        "PCH": "c:\\workspace\\sideproject1\\engine\\intermediate\\build\\win64\\x64\\unrealeditor\\development\\engine\\sharedpch.engine.shadowerrors.h.pch",
        "Includes": [
            "c:\\workspace\\sideproject1\\engine\\intermediate\\build\\win64\\x64\\unrealeditor\\development\\webbrowser\\definitions.webbrowser.h",
            "c:\\workspace\\sideproject1\\engine\\intermediate\\build\\win64\\unrealeditor\\inc\\webbrowser\\uht\\webbrowser.init.gen.cpp",
            "c:\\workspace\\sideproject1\\engine\\source\\runtime\\webbrowser\\private\\cef\\cefbrowserapp.cpp",
            "c:\\workspace\\sideproject1\\engine\\source\\runtime\\webbrowser\\private\\cef\\cefbrowserapp.h",
            "c:\\workspace\\sideproject1\\engine\\source\\runtime\\webbrowser\\private\\cef\\ceflibcefincludes.h",
            "c:\\workspace\\sideproject1\\engine\\source\\runtime\\core\\public\\windows\\windowshwrapper.h",
            "c:\\workspace\\sideproject1\\engine\\source\\runtime\\core\\public\\windows\\prewindowsapi.h",
            "c:\\workspace\\sideproject1\\engine\\source\\runtime\\core\\public\\windows\\minwindows.h",
            "c:\\program files (x86)\\windows kits\\10\\include\\10.0.19041.0\\um\\windows.h",
            "c:\\program files (x86)\\windows kits\\10\\include\\10.0.19041.0\\shared\\sdkddkver.h",
            "c:\\program files (x86)\\microsoft visual studio\\2019\\community\\vc\\tools\\msvc\\14.29.30133\\include\\excpt.h",
            "c:\\program files (x86)\\windows kits\\10\\include\\10.0.19041.0\\shared\\windef.h",
            "c:\\program files (x86)\\windows kits\\10\\include\\10.0.19041.0\\shared\\minwindef.h",
            "c:\\program files (x86)\\windows kits\\10\\include\\10.0.19041.0\\um\\winnt.h",
            "c:\\program files (x86)\\windows kits\\10\\include\\10.0.19041.0\\shared\\kernelspecs.h",
            "c:\\program files (x86)\\windows kits\\10\\include\\10.0.19041.0\\shared\\basetsd.h",
            "c:\\program files (x86)\\windows kits\\10\\include\\10.0.19041.0\\shared\\guiddef.h",
            "c:\\program files (x86)\\windows kits\\10\\include\\10.0.19041.0\\shared\\pshpack4.h",
            "c:\\program files (x86)\\windows kits\\10\\include\\10.0.19041.0\\shared\\poppack.h",
            "c:\\program files (x86)\\windows kits\\10\\include\\10.0.19041.0\\shared\\pshpack4.h",
            "c:\\program files (x86)\\windows kits\\10\\include\\10.0.19041.0\\shared\\poppack.h",
            "c:\\program files (x86)\\windows kits\\10\\include\\10.0.19041.0\\shared\\pshpack4.h",
            "c:\\program files (x86)\\windows kits\\10\\include\\10.0.19041.0\\shared\\pshpack2.h",
            "c:\\program files (x86)\\windows kits\\10\\include\\10.0.19041.0\\shared\\poppack.h",
            "c:\\program files (x86)\\windows kits\\10\\include\\10.0.19041.0\\shared\\pshpack2.h",
            "c:\\program files (x86)\\windows kits\\10\\include\\10.0.19041.0\\shared\\pshpack2.h",
            "c:\\program files (x86)\\windows kits\\10\\include\\10.0.19041.0\\shared\\poppack.h",
            "c:\\program files (x86)\\windows kits\\10\\include\\10.0.19041.0\\shared\\poppack.h",
            "c:\\program files (x86)\\windows kits\\10\\include\\10.0.19041.0\\shared\\pshpack8.h",
            "c:\\program files (x86)\\windows kits\\10\\include\\10.0.19041.0\\shared\\poppack.h",
            "c:\\program files (x86)\\windows kits\\10\\include\\10.0.19041.0\\shared\\pshpack1.h",
            "c:\\program files (x86)\\windows kits\\10\\include\\10.0.19041.0\\shared\\poppack.h",
            "c:\\program files (x86)\\windows kits\\10\\include\\10.0.19041.0\\shared\\pshpack1.h",
            "c:\\program files (x86)\\windows kits\\10\\include\\10.0.19041.0\\shared\\poppack.h",
            "c:\\program files (x86)\\windows kits\\10\\include\\10.0.19041.0\\shared\\poppack.h",
            "c:\\program files (x86)\\windows kits\\10\\include\\10.0.19041.0\\shared\\apiset.h",
            "c:\\program files (x86)\\windows kits\\10\\include\\10.0.19041.0\\shared\\ktmtypes.h",
            "c:\\program files (x86)\\windows kits\\10\\include\\10.0.19041.0\\um\\winbase.h",
            "c:\\program files (x86)\\windows kits\\10\\include\\10.0.19041.0\\shared\\apisetcconv.h",
            "c:\\program files (x86)\\windows kits\\10\\include\\10.0.19041.0\\um\\minwinbase.h",
            "c:\\program files (x86)\\windows kits\\10\\include\\10.0.19041.0\\um\\apiquery2.h",
            "c:\\program files (x86)\\windows kits\\10\\include\\10.0.19041.0\\um\\processenv.h",
            "c:\\program files (x86)\\windows kits\\10\\include\\10.0.19041.0\\um\\fileapifromapp.h",
            "c:\\program files (x86)\\windows kits\\10\\include\\10.0.19041.0\\um\\fileapi.h",
            "c:\\program files (x86)\\windows kits\\10\\include\\10.0.19041.0\\um\\debugapi.h",
            "c:\\program files (x86)\\windows kits\\10\\include\\10.0.19041.0\\um\\utilapiset.h",
            "c:\\program files (x86)\\windows kits\\10\\include\\10.0.19041.0\\um\\handleapi.h",
            "c:\\program files (x86)\\windows kits\\10\\include\\10.0.19041.0\\um\\errhandlingapi.h",
            "c:\\program files (x86)\\windows kits\\10\\include\\10.0.19041.0\\um\\fibersapi.h",
            "c:\\program files (x86)\\windows kits\\10\\include\\10.0.19041.0\\um\\namedpipeapi.h",
            "c:\\program files (x86)\\windows kits\\10\\include\\10.0.19041.0\\um\\profileapi.h",
            "c:\\program files (x86)\\windows kits\\10\\include\\10.0.19041.0\\um\\heapapi.h",
            "c:\\program files (x86)\\windows kits\\10\\include\\10.0.19041.0\\um\\ioapiset.h",
            "c:\\program files (x86)\\windows kits\\10\\include\\10.0.19041.0\\um\\synchapi.h",
            "c:\\program files (x86)\\windows kits\\10\\include\\10.0.19041.0\\um\\interlockedapi.h",
            "c:\\program files (x86)\\windows kits\\10\\include\\10.0.19041.0\\um\\processthreadsapi.h",
            "c:\\program files (x86)\\windows kits\\10\\include\\10.0.19041.0\\um\\sysinfoapi.h",
            "c:\\program files (x86)\\windows kits\\10\\include\\10.0.19041.0\\um\\memoryapi.h",
            "c:\\program files (x86)\\windows kits\\10\\include\\10.0.19041.0\\um\\enclaveapi.h",
            "c:\\program files (x86)\\windows kits\\10\\include\\10.0.19041.0\\um\\threadpoollegacyapiset.h",
            "c:\\program files (x86)\\windows kits\\10\\include\\10.0.19041.0\\um\\threadpoolapiset.h",
            "c:\\program files (x86)\\windows kits\\10\\include\\10.0.19041.0\\um\\jobapi.h",
            "c:\\program files (x86)\\windows kits\\10\\include\\10.0.19041.0\\um\\jobapi2.h",
            "c:\\program files (x86)\\windows kits\\10\\include\\10.0.19041.0\\um\\wow64apiset.h",
            "c:\\program files (x86)\\windows kits\\10\\include\\10.0.19041.0\\um\\libloaderapi.h",
            "c:\\program files (x86)\\windows kits\\10\\include\\10.0.19041.0\\um\\securitybaseapi.h",
            "c:\\program files (x86)\\windows kits\\10\\include\\10.0.19041.0\\um\\namespaceapi.h",
            "c:\\program files (x86)\\windows kits\\10\\include\\10.0.19041.0\\um\\systemtopologyapi.h",
            "c:\\program files (x86)\\windows kits\\10\\include\\10.0.19041.0\\um\\processtopologyapi.h",
            "c:\\program files (x86)\\windows kits\\10\\include\\10.0.19041.0\\um\\securityappcontainer.h",
            "c:\\program files (x86)\\windows kits\\10\\include\\10.0.19041.0\\um\\realtimeapiset.h",
            "c:\\program files (x86)\\windows kits\\10\\include\\10.0.19041.0\\shared\\winerror.h",
            "c:\\program files (x86)\\windows kits\\10\\include\\10.0.19041.0\\um\\timezoneapi.h",
            "c:\\program files (x86)\\windows kits\\10\\include\\10.0.19041.0\\um\\wingdi.h",
            "c:\\program files (x86)\\windows kits\\10\\include\\10.0.19041.0\\shared\\pshpack1.h",
            "c:\\program files (x86)\\windows kits\\10\\include\\10.0.19041.0\\shared\\poppack.h",
            "c:\\program files (x86)\\windows kits\\10\\include\\10.0.19041.0\\shared\\pshpack2.h",
            "c:\\program files (x86)\\windows kits\\10\\include\\10.0.19041.0\\shared\\poppack.h",
            "c:\\program files (x86)\\windows kits\\10\\include\\10.0.19041.0\\shared\\pshpack4.h",
            "c:\\program files (x86)\\windows kits\\10\\include\\10.0.19041.0\\shared\\poppack.h",
            "c:\\program files (x86)\\windows kits\\10\\include\\10.0.19041.0\\shared\\pshpack4.h",
            "c:\\program files (x86)\\windows kits\\10\\include\\10.0.19041.0\\shared\\poppack.h",
            "c:\\program files (x86)\\windows kits\\10\\include\\10.0.19041.0\\um\\winuser.h",
            "c:\\program files (x86)\\windows kits\\10\\include\\10.0.19041.0\\shared\\pshpack2.h",
            "c:\\program files (x86)\\windows kits\\10\\include\\10.0.19041.0\\shared\\poppack.h",
            "c:\\program files (x86)\\windows kits\\10\\include\\10.0.19041.0\\shared\\tvout.h",
            "c:\\program files (x86)\\windows kits\\10\\include\\10.0.19041.0\\um\\winnls.h",
            "c:\\program files (x86)\\windows kits\\10\\include\\10.0.19041.0\\um\\datetimeapi.h",
            "c:\\program files (x86)\\windows kits\\10\\include\\10.0.19041.0\\um\\stringapiset.h",
            "c:\\program files (x86)\\windows kits\\10\\include\\10.0.19041.0\\um\\winnls.h",
            "c:\\program files (x86)\\windows kits\\10\\include\\10.0.19041.0\\um\\wincon.h",
            "c:\\program files (x86)\\windows kits\\10\\include\\10.0.19041.0\\um\\wincontypes.h",
            "c:\\program files (x86)\\windows kits\\10\\include\\10.0.19041.0\\um\\consoleapi.h",
            "c:\\program files (x86)\\windows kits\\10\\include\\10.0.19041.0\\um\\consoleapi2.h",
            "c:\\program files (x86)\\windows kits\\10\\include\\10.0.19041.0\\um\\consoleapi3.h",
            "c:\\program files (x86)\\windows kits\\10\\include\\10.0.19041.0\\um\\winver.h",
            "c:\\program files (x86)\\windows kits\\10\\include\\10.0.19041.0\\um\\verrsrc.h",
            "c:\\program files (x86)\\windows kits\\10\\include\\10.0.19041.0\\um\\winreg.h",
            "c:\\program files (x86)\\windows kits\\10\\include\\10.0.19041.0\\um\\reason.h",
            "c:\\program files (x86)\\windows kits\\10\\include\\10.0.19041.0\\um\\winnetwk.h",
            "c:\\program files (x86)\\windows kits\\10\\include\\10.0.19041.0\\shared\\wnnc.h",
            "c:\\program files (x86)\\windows kits\\10\\include\\10.0.19041.0\\shared\\stralign.h",
            "c:\\program files (x86)\\windows kits\\10\\include\\10.0.19041.0\\um\\imm.h",
            "c:\\program files (x86)\\windows kits\\10\\include\\10.0.19041.0\\um\\ime_cmodes.h",
            "c:\\workspace\\sideproject1\\engine\\source\\runtime\\core\\public\\windows\\postwindowsapi.h",
            "c:\\workspace\\sideproject1\\engine\\source\\runtime\\core\\public\\windows\\allowwindowsplatformtypes.h",
            "c:\\workspace\\sideproject1\\engine\\source\\runtime\\core\\public\\windows\\allowwindowsplatformatomics.h",
            "c:\\workspace\\sideproject1\\engine\\source\\thirdparty\\cef3\\cef_binary_90.6.7+g19ba721+chromium-90.0.4430.212_windows64\\include\\cef_app.h",
            "c:\\workspace\\sideproject1\\engine\\source\\thirdparty\\cef3\\cef_binary_90.6.7+g19ba721+chromium-90.0.4430.212_windows64\\include\\cef_base.h",
            "c:\\workspace\\sideproject1\\engine\\source\\thirdparty\\cef3\\cef_binary_90.6.7+g19ba721+chromium-90.0.4430.212_windows64\\include\\base\\cef_atomic_ref_count.h",
            "c:\\workspace\\sideproject1\\engine\\source\\thirdparty\\cef3\\cef_binary_90.6.7+g19ba721+chromium-90.0.4430.212_windows64\\include\\base\\cef_atomicops.h",
            "c:\\workspace\\sideproject1\\engine\\source\\thirdparty\\cef3\\cef_binary_90.6.7+g19ba721+chromium-90.0.4430.212_windows64\\include\\base\\cef_build.h",
            "c:\\workspace\\sideproject1\\engine\\source\\thirdparty\\cef3\\cef_binary_90.6.7+g19ba721+chromium-90.0.4430.212_windows64\\include\\base\\internal\\cef_atomicops_x86_msvc.h",
            "c:\\workspace\\sideproject1\\engine\\source\\thirdparty\\cef3\\cef_binary_90.6.7+g19ba721+chromium-90.0.4430.212_windows64\\include\\base\\cef_macros.h",
            "c:\\workspace\\sideproject1\\engine\\source\\thirdparty\\cef3\\cef_binary_90.6.7+g19ba721+chromium-90.0.4430.212_windows64\\include\\internal\\cef_ptr.h",
            "c:\\workspace\\sideproject1\\engine\\source\\thirdparty\\cef3\\cef_binary_90.6.7+g19ba721+chromium-90.0.4430.212_windows64\\include\\base\\cef_ref_counted.h",
            "c:\\program files (x86)\\microsoft visual studio\\2019\\community\\vc\\tools\\msvc\\14.29.30133\\include\\cassert",
            "c:\\program files (x86)\\windows kits\\10\\include\\10.0.19041.0\\ucrt\\assert.h",
            "c:\\workspace\\sideproject1\\engine\\source\\thirdparty\\cef3\\cef_binary_90.6.7+g19ba721+chromium-90.0.4430.212_windows64\\include\\base\\cef_logging.h",
            "c:\\program files (x86)\\microsoft visual studio\\2019\\community\\vc\\tools\\msvc\\14.29.30133\\include\\cassert",
            "c:\\program files (x86)\\windows kits\\10\\include\\10.0.19041.0\\ucrt\\assert.h",
            "c:\\program files (x86)\\microsoft visual studio\\2019\\community\\vc\\tools\\msvc\\14.29.30133\\include\\sstream",
            "c:\\program files (x86)\\microsoft visual studio\\2019\\community\\vc\\tools\\msvc\\14.29.30133\\include\\istream",
            "c:\\program files (x86)\\microsoft visual studio\\2019\\community\\vc\\tools\\msvc\\14.29.30133\\include\\ostream",
            "c:\\program files (x86)\\microsoft visual studio\\2019\\community\\vc\\tools\\msvc\\14.29.30133\\include\\ios",
            "c:\\program files (x86)\\microsoft visual studio\\2019\\community\\vc\\tools\\msvc\\14.29.30133\\include\\xlocnum",
            "c:\\program files (x86)\\microsoft visual studio\\2019\\community\\vc\\tools\\msvc\\14.29.30133\\include\\cmath",
            "c:\\program files (x86)\\microsoft visual studio\\2019\\community\\vc\\tools\\msvc\\14.29.30133\\include\\iterator",
            "c:\\program files (x86)\\microsoft visual studio\\2019\\community\\vc\\tools\\msvc\\14.29.30133\\include\\iosfwd",
            "c:\\program files (x86)\\microsoft visual studio\\2019\\community\\vc\\tools\\msvc\\14.29.30133\\include\\streambuf",
            "c:\\program files (x86)\\microsoft visual studio\\2019\\community\\vc\\tools\\msvc\\14.29.30133\\include\\xiosbase",
            "c:\\program files (x86)\\windows kits\\10\\include\\10.0.19041.0\\ucrt\\share.h",
            "c:\\program files (x86)\\microsoft visual studio\\2019\\community\\vc\\tools\\msvc\\14.29.30133\\include\\system_error",
            "c:\\program files (x86)\\microsoft visual studio\\2019\\community\\vc\\tools\\msvc\\14.29.30133\\include\\__msvc_system_error_abi.hpp",
            "c:\\program files (x86)\\microsoft visual studio\\2019\\community\\vc\\tools\\msvc\\14.29.30133\\include\\cerrno",
            "c:\\program files (x86)\\microsoft visual studio\\2019\\community\\vc\\tools\\msvc\\14.29.30133\\include\\stdexcept",
            "c:\\program files (x86)\\microsoft visual studio\\2019\\community\\vc\\tools\\msvc\\14.29.30133\\include\\xstring",
            "c:\\program files (x86)\\microsoft visual studio\\2019\\community\\vc\\tools\\msvc\\14.29.30133\\include\\xmemory",
            "c:\\program files (x86)\\microsoft visual studio\\2019\\community\\vc\\tools\\msvc\\14.29.30133\\include\\xpolymorphic_allocator.h",
            "c:\\program files (x86)\\microsoft visual studio\\2019\\community\\vc\\tools\\msvc\\14.29.30133\\include\\xcall_once.h",
            "c:\\program files (x86)\\microsoft visual studio\\2019\\community\\vc\\tools\\msvc\\14.29.30133\\include\\xerrc.h",
            "c:\\program files (x86)\\microsoft visual studio\\2019\\community\\vc\\tools\\msvc\\14.29.30133\\include\\xlocale",
            "c:\\program files (x86)\\microsoft visual studio\\2019\\community\\vc\\tools\\msvc\\14.29.30133\\include\\memory",
            "c:\\program files (x86)\\microsoft visual studio\\2019\\community\\vc\\tools\\msvc\\14.29.30133\\include\\xfacet",
            "c:\\program files (x86)\\microsoft visual studio\\2019\\community\\vc\\tools\\msvc\\14.29.30133\\include\\xlocinfo",
            "c:\\program files (x86)\\microsoft visual studio\\2019\\community\\vc\\tools\\msvc\\14.29.30133\\include\\xlocinfo.h",
            "c:\\program files (x86)\\microsoft visual studio\\2019\\community\\vc\\tools\\msvc\\14.29.30133\\include\\cctype",
            "c:\\program files (x86)\\microsoft visual studio\\2019\\community\\vc\\tools\\msvc\\14.29.30133\\include\\clocale",
            "c:\\program files (x86)\\windows kits\\10\\include\\10.0.19041.0\\ucrt\\locale.h",
            "c:\\program files (x86)\\microsoft visual studio\\2019\\community\\vc\\tools\\msvc\\14.29.30133\\include\\string",
            "c:\\workspace\\sideproject1\\engine\\source\\thirdparty\\cef3\\cef_binary_90.6.7+g19ba721+chromium-90.0.4430.212_windows64\\include\\internal\\cef_logging_internal.h",
            "c:\\workspace\\sideproject1\\engine\\source\\thirdparty\\cef3\\cef_binary_90.6.7+g19ba721+chromium-90.0.4430.212_windows64\\include\\internal\\cef_export.h",
            "c:\\workspace\\sideproject1\\engine\\source\\thirdparty\\cef3\\cef_binary_90.6.7+g19ba721+chromium-90.0.4430.212_windows64\\include\\base\\cef_scoped_ptr.h",
            "c:\\program files (x86)\\windows kits\\10\\include\\10.0.19041.0\\ucrt\\assert.h",
            "c:\\program files (x86)\\microsoft visual studio\\2019\\community\\vc\\tools\\msvc\\14.29.30133\\include\\algorithm",
            "c:\\workspace\\sideproject1\\engine\\source\\thirdparty\\cef3\\cef_binary_90.6.7+g19ba721+chromium-90.0.4430.212_windows64\\include\\base\\cef_basictypes.h",
            "c:\\workspace\\sideproject1\\engine\\source\\thirdparty\\cef3\\cef_binary_90.6.7+g19ba721+chromium-90.0.4430.212_windows64\\include\\base\\cef_move.h",
            "c:\\workspace\\sideproject1\\engine\\source\\thirdparty\\cef3\\cef_binary_90.6.7+g19ba721+chromium-90.0.4430.212_windows64\\include\\base\\cef_template_util.h",
            "c:\\workspace\\sideproject1\\engine\\source\\thirdparty\\cef3\\cef_binary_90.6.7+g19ba721+chromium-90.0.4430.212_windows64\\include\\internal\\cef_types_wrappers.h",
            "c:\\workspace\\sideproject1\\engine\\source\\thirdparty\\cef3\\cef_binary_90.6.7+g19ba721+chromium-90.0.4430.212_windows64\\include\\internal\\cef_string.h",
            "c:\\workspace\\sideproject1\\engine\\source\\thirdparty\\cef3\\cef_binary_90.6.7+g19ba721+chromium-90.0.4430.212_windows64\\include\\internal\\cef_string_types.h",
            "c:\\workspace\\sideproject1\\engine\\source\\thirdparty\\cef3\\cef_binary_90.6.7+g19ba721+chromium-90.0.4430.212_windows64\\include\\internal\\cef_string_wrappers.h",
            "c:\\program files (x86)\\windows kits\\10\\include\\10.0.19041.0\\ucrt\\memory.h",
            "c:\\workspace\\sideproject1\\engine\\source\\thirdparty\\cef3\\cef_binary_90.6.7+g19ba721+chromium-90.0.4430.212_windows64\\include\\base\\cef_string16.h",
            "c:\\workspace\\sideproject1\\engine\\source\\thirdparty\\cef3\\cef_binary_90.6.7+g19ba721+chromium-90.0.4430.212_windows64\\include\\internal\\cef_string_list.h",
            "c:\\workspace\\sideproject1\\engine\\source\\thirdparty\\cef3\\cef_binary_90.6.7+g19ba721+chromium-90.0.4430.212_windows64\\include\\internal\\cef_types.h",
            "c:\\workspace\\sideproject1\\engine\\source\\thirdparty\\cef3\\cef_binary_90.6.7+g19ba721+chromium-90.0.4430.212_windows64\\include\\internal\\cef_time.h",
            "c:\\workspace\\sideproject1\\engine\\source\\thirdparty\\cef3\\cef_binary_90.6.7+g19ba721+chromium-90.0.4430.212_windows64\\include\\internal\\cef_types_win.h",
            "c:\\workspace\\sideproject1\\engine\\source\\thirdparty\\cef3\\cef_binary_90.6.7+g19ba721+chromium-90.0.4430.212_windows64\\include\\base\\internal\\cef_net_error_list.h",
            "c:\\workspace\\sideproject1\\engine\\source\\thirdparty\\cef3\\cef_binary_90.6.7+g19ba721+chromium-90.0.4430.212_windows64\\include\\internal\\cef_win.h",
            "c:\\workspace\\sideproject1\\engine\\source\\thirdparty\\cef3\\cef_binary_90.6.7+g19ba721+chromium-90.0.4430.212_windows64\\include\\cef_browser_process_handler.h",
            "c:\\workspace\\sideproject1\\engine\\source\\thirdparty\\cef3\\cef_binary_90.6.7+g19ba721+chromium-90.0.4430.212_windows64\\include\\cef_client.h",
            "c:\\workspace\\sideproject1\\engine\\source\\thirdparty\\cef3\\cef_binary_90.6.7+g19ba721+chromium-90.0.4430.212_windows64\\include\\cef_audio_handler.h",
            "c:\\workspace\\sideproject1\\engine\\source\\thirdparty\\cef3\\cef_binary_90.6.7+g19ba721+chromium-90.0.4430.212_windows64\\include\\cef_browser.h",
            "c:\\program files (x86)\\microsoft visual studio\\2019\\community\\vc\\tools\\msvc\\14.29.30133\\include\\vector",
            "c:\\workspace\\sideproject1\\engine\\source\\thirdparty\\cef3\\cef_binary_90.6.7+g19ba721+chromium-90.0.4430.212_windows64\\include\\cef_devtools_message_observer.h",
            "c:\\workspace\\sideproject1\\engine\\source\\thirdparty\\cef3\\cef_binary_90.6.7+g19ba721+chromium-90.0.4430.212_windows64\\include\\cef_drag_data.h",
            "c:\\workspace\\sideproject1\\engine\\source\\thirdparty\\cef3\\cef_binary_90.6.7+g19ba721+chromium-90.0.4430.212_windows64\\include\\cef_image.h",
            "c:\\workspace\\sideproject1\\engine\\source\\thirdparty\\cef3\\cef_binary_90.6.7+g19ba721+chromium-90.0.4430.212_windows64\\include\\cef_values.h",
            "c:\\workspace\\sideproject1\\engine\\source\\thirdparty\\cef3\\cef_binary_90.6.7+g19ba721+chromium-90.0.4430.212_windows64\\include\\cef_stream.h",
            "c:\\workspace\\sideproject1\\engine\\source\\thirdparty\\cef3\\cef_binary_90.6.7+g19ba721+chromium-90.0.4430.212_windows64\\include\\cef_frame.h",
            "c:\\workspace\\sideproject1\\engine\\source\\thirdparty\\cef3\\cef_binary_90.6.7+g19ba721+chromium-90.0.4430.212_windows64\\include\\cef_dom.h",
            "c:\\program files (x86)\\microsoft visual studio\\2019\\community\\vc\\tools\\msvc\\14.29.30133\\include\\map",
            "c:\\program files (x86)\\microsoft visual studio\\2019\\community\\vc\\tools\\msvc\\14.29.30133\\include\\xtree",
            "c:\\program files (x86)\\microsoft visual studio\\2019\\community\\vc\\tools\\msvc\\14.29.30133\\include\\xnode_handle.h",
            "c:\\workspace\\sideproject1\\engine\\source\\thirdparty\\cef3\\cef_binary_90.6.7+g19ba721+chromium-90.0.4430.212_windows64\\include\\cef_process_message.h",
            "c:\\workspace\\sideproject1\\engine\\source\\thirdparty\\cef3\\cef_binary_90.6.7+g19ba721+chromium-90.0.4430.212_windows64\\include\\cef_request.h",
            "c:\\workspace\\sideproject1\\engine\\source\\thirdparty\\cef3\\cef_binary_90.6.7+g19ba721+chromium-90.0.4430.212_windows64\\include\\cef_string_visitor.h",
            "c:\\workspace\\sideproject1\\engine\\source\\thirdparty\\cef3\\cef_binary_90.6.7+g19ba721+chromium-90.0.4430.212_windows64\\include\\cef_navigation_entry.h",
            "c:\\workspace\\sideproject1\\engine\\source\\thirdparty\\cef3\\cef_binary_90.6.7+g19ba721+chromium-90.0.4430.212_windows64\\include\\cef_ssl_status.h",
            "c:\\workspace\\sideproject1\\engine\\source\\thirdparty\\cef3\\cef_binary_90.6.7+g19ba721+chromium-90.0.4430.212_windows64\\include\\cef_x509_certificate.h",
            "c:\\workspace\\sideproject1\\engine\\source\\thirdparty\\cef3\\cef_binary_90.6.7+g19ba721+chromium-90.0.4430.212_windows64\\include\\cef_registration.h",
            "c:\\workspace\\sideproject1\\engine\\source\\thirdparty\\cef3\\cef_binary_90.6.7+g19ba721+chromium-90.0.4430.212_windows64\\include\\cef_request_context.h",
            "c:\\workspace\\sideproject1\\engine\\source\\thirdparty\\cef3\\cef_binary_90.6.7+g19ba721+chromium-90.0.4430.212_windows64\\include\\cef_callback.h",
            "c:\\workspace\\sideproject1\\engine\\source\\thirdparty\\cef3\\cef_binary_90.6.7+g19ba721+chromium-90.0.4430.212_windows64\\include\\cef_cookie.h",
            "c:\\workspace\\sideproject1\\engine\\source\\thirdparty\\cef3\\cef_binary_90.6.7+g19ba721+chromium-90.0.4430.212_windows64\\include\\cef_extension.h",
            "c:\\workspace\\sideproject1\\engine\\source\\thirdparty\\cef3\\cef_binary_90.6.7+g19ba721+chromium-90.0.4430.212_windows64\\include\\cef_extension_handler.h",
            "c:\\workspace\\sideproject1\\engine\\source\\thirdparty\\cef3\\cef_binary_90.6.7+g19ba721+chromium-90.0.4430.212_windows64\\include\\cef_media_router.h",
            "c:\\workspace\\sideproject1\\engine\\source\\thirdparty\\cef3\\cef_binary_90.6.7+g19ba721+chromium-90.0.4430.212_windows64\\include\\cef_context_menu_handler.h",
            "c:\\workspace\\sideproject1\\engine\\source\\thirdparty\\cef3\\cef_binary_90.6.7+g19ba721+chromium-90.0.4430.212_windows64\\include\\cef_menu_model.h",
            "c:\\workspace\\sideproject1\\engine\\source\\thirdparty\\cef3\\cef_binary_90.6.7+g19ba721+chromium-90.0.4430.212_windows64\\include\\cef_menu_model_delegate.h",
            "c:\\workspace\\sideproject1\\engine\\source\\thirdparty\\cef3\\cef_binary_90.6.7+g19ba721+chromium-90.0.4430.212_windows64\\include\\cef_dialog_handler.h",
            "c:\\workspace\\sideproject1\\engine\\source\\thirdparty\\cef3\\cef_binary_90.6.7+g19ba721+chromium-90.0.4430.212_windows64\\include\\cef_display_handler.h",
            "c:\\workspace\\sideproject1\\engine\\source\\thirdparty\\cef3\\cef_binary_90.6.7+g19ba721+chromium-90.0.4430.212_windows64\\include\\cef_download_handler.h",
            "c:\\workspace\\sideproject1\\engine\\source\\thirdparty\\cef3\\cef_binary_90.6.7+g19ba721+chromium-90.0.4430.212_windows64\\include\\cef_download_item.h",
            "c:\\workspace\\sideproject1\\engine\\source\\thirdparty\\cef3\\cef_binary_90.6.7+g19ba721+chromium-90.0.4430.212_windows64\\include\\cef_drag_handler.h",
            "c:\\workspace\\sideproject1\\engine\\source\\thirdparty\\cef3\\cef_binary_90.6.7+g19ba721+chromium-90.0.4430.212_windows64\\include\\cef_find_handler.h",
            "c:\\workspace\\sideproject1\\engine\\source\\thirdparty\\cef3\\cef_binary_90.6.7+g19ba721+chromium-90.0.4430.212_windows64\\include\\cef_focus_handler.h",
            "c:\\workspace\\sideproject1\\engine\\source\\thirdparty\\cef3\\cef_binary_90.6.7+g19ba721+chromium-90.0.4430.212_windows64\\include\\cef_jsdialog_handler.h",
            "c:\\workspace\\sideproject1\\engine\\source\\thirdparty\\cef3\\cef_binary_90.6.7+g19ba721+chromium-90.0.4430.212_windows64\\include\\cef_keyboard_handler.h",
            "c:\\workspace\\sideproject1\\engine\\source\\thirdparty\\cef3\\cef_binary_90.6.7+g19ba721+chromium-90.0.4430.212_windows64\\include\\cef_life_span_handler.h",
            "c:\\workspace\\sideproject1\\engine\\source\\thirdparty\\cef3\\cef_binary_90.6.7+g19ba721+chromium-90.0.4430.212_windows64\\include\\cef_load_handler.h",
            "c:\\workspace\\sideproject1\\engine\\source\\thirdparty\\cef3\\cef_binary_90.6.7+g19ba721+chromium-90.0.4430.212_windows64\\include\\cef_print_handler.h",
            "c:\\workspace\\sideproject1\\engine\\source\\thirdparty\\cef3\\cef_binary_90.6.7+g19ba721+chromium-90.0.4430.212_windows64\\include\\cef_print_settings.h",
            "c:\\workspace\\sideproject1\\engine\\source\\thirdparty\\cef3\\cef_binary_90.6.7+g19ba721+chromium-90.0.4430.212_windows64\\include\\cef_render_handler.h",
            "c:\\workspace\\sideproject1\\engine\\source\\thirdparty\\cef3\\cef_binary_90.6.7+g19ba721+chromium-90.0.4430.212_windows64\\include\\cef_accessibility_handler.h",
            "c:\\workspace\\sideproject1\\engine\\source\\thirdparty\\cef3\\cef_binary_90.6.7+g19ba721+chromium-90.0.4430.212_windows64\\include\\cef_request_handler.h",
            "c:\\workspace\\sideproject1\\engine\\source\\thirdparty\\cef3\\cef_binary_90.6.7+g19ba721+chromium-90.0.4430.212_windows64\\include\\cef_auth_callback.h",
            "c:\\workspace\\sideproject1\\engine\\source\\thirdparty\\cef3\\cef_binary_90.6.7+g19ba721+chromium-90.0.4430.212_windows64\\include\\cef_request_callback.h",
            "c:\\workspace\\sideproject1\\engine\\source\\thirdparty\\cef3\\cef_binary_90.6.7+g19ba721+chromium-90.0.4430.212_windows64\\include\\cef_resource_request_handler.h",
            "c:\\workspace\\sideproject1\\engine\\source\\thirdparty\\cef3\\cef_binary_90.6.7+g19ba721+chromium-90.0.4430.212_windows64\\include\\cef_resource_handler.h",
            "c:\\workspace\\sideproject1\\engine\\source\\thirdparty\\cef3\\cef_binary_90.6.7+g19ba721+chromium-90.0.4430.212_windows64\\include\\cef_response.h",
            "c:\\workspace\\sideproject1\\engine\\source\\thirdparty\\cef3\\cef_binary_90.6.7+g19ba721+chromium-90.0.4430.212_windows64\\include\\cef_response_filter.h",
            "c:\\workspace\\sideproject1\\engine\\source\\thirdparty\\cef3\\cef_binary_90.6.7+g19ba721+chromium-90.0.4430.212_windows64\\include\\cef_ssl_info.h",
            "c:\\workspace\\sideproject1\\engine\\source\\thirdparty\\cef3\\cef_binary_90.6.7+g19ba721+chromium-90.0.4430.212_windows64\\include\\cef_command_line.h",
            "c:\\workspace\\sideproject1\\engine\\source\\thirdparty\\cef3\\cef_binary_90.6.7+g19ba721+chromium-90.0.4430.212_windows64\\include\\cef_render_process_handler.h",
            "c:\\workspace\\sideproject1\\engine\\source\\thirdparty\\cef3\\cef_binary_90.6.7+g19ba721+chromium-90.0.4430.212_windows64\\include\\cef_v8.h",
            "c:\\workspace\\sideproject1\\engine\\source\\thirdparty\\cef3\\cef_binary_90.6.7+g19ba721+chromium-90.0.4430.212_windows64\\include\\cef_task.h",
            "c:\\workspace\\sideproject1\\engine\\source\\thirdparty\\cef3\\cef_binary_90.6.7+g19ba721+chromium-90.0.4430.212_windows64\\include\\cef_resource_bundle_handler.h",
            "c:\\workspace\\sideproject1\\engine\\source\\thirdparty\\cef3\\cef_binary_90.6.7+g19ba721+chromium-90.0.4430.212_windows64\\include\\cef_scheme.h",
            "c:\\workspace\\sideproject1\\engine\\source\\thirdparty\\cef3\\cef_binary_90.6.7+g19ba721+chromium-90.0.4430.212_windows64\\include\\cef_request_context_handler.h",
            "c:\\workspace\\sideproject1\\engine\\source\\thirdparty\\cef3\\cef_binary_90.6.7+g19ba721+chromium-90.0.4430.212_windows64\\include\\cef_web_plugin.h",
            "c:\\workspace\\sideproject1\\engine\\source\\thirdparty\\cef3\\cef_binary_90.6.7+g19ba721+chromium-90.0.4430.212_windows64\\include\\cef_origin_whitelist.h",
            "c:\\workspace\\sideproject1\\engine\\source\\runtime\\core\\public\\windows\\hidewindowsplatformatomics.h",
            "c:\\workspace\\sideproject1\\engine\\source\\runtime\\core\\public\\windows\\hidewindowsplatformtypes.h",
            "c:\\workspace\\sideproject1\\engine\\source\\runtime\\webbrowser\\private\\webbrowserlog.h",
            "c:\\workspace\\sideproject1\\engine\\source\\runtime\\webbrowser\\private\\cef\\cefbrowserbyteresource.cpp",
            "c:\\workspace\\sideproject1\\engine\\source\\runtime\\webbrowser\\private\\cef\\cefbrowserbyteresource.h",
            "c:\\workspace\\sideproject1\\engine\\source\\runtime\\webbrowser\\private\\cef\\cefbrowserhandler.cpp",
            "c:\\workspace\\sideproject1\\engine\\source\\runtime\\webbrowser\\private\\cef\\cefbrowserhandler.h",
            "c:\\workspace\\sideproject1\\engine\\source\\runtime\\webbrowser\\public\\iwebbrowserwindow.h",
            "c:\\workspace\\sideproject1\\engine\\source\\runtime\\webbrowser\\public\\swebbrowser.h",
            "c:\\workspace\\sideproject1\\engine\\source\\runtime\\webbrowser\\public\\swebbrowserview.h",
            "c:\\workspace\\sideproject1\\engine\\source\\runtime\\slate\\public\\widgets\\sviewport.h",
            "c:\\workspace\\sideproject1\\engine\\source\\runtime\\webbrowser\\public\\iwebbrowsersingleton.h",
            "c:\\workspace\\sideproject1\\engine\\source\\runtime\\webbrowser\\public\\iwebbrowserresourceloader.h",
            "c:\\workspace\\sideproject1\\engine\\source\\runtime\\applicationcore\\public\\hal\\platformapplicationmisc.h",
            "c:\\workspace\\sideproject1\\engine\\source\\runtime\\applicationcore\\public\\windows\\windowsplatformapplicationmisc.h",
            "c:\\workspace\\sideproject1\\engine\\source\\runtime\\applicationcore\\public\\genericplatform\\genericplatformapplicationmisc.h",
            "c:\\workspace\\sideproject1\\engine\\source\\runtime\\webbrowser\\public\\webbrowsermodule.h",
            "c:\\workspace\\sideproject1\\engine\\source\\runtime\\webbrowser\\private\\cef\\cefbrowserclosuretask.h",
            "c:\\workspace\\sideproject1\\engine\\source\\runtime\\webbrowser\\private\\webbrowsersingleton.h",
            "c:\\workspace\\sideproject1\\engine\\source\\runtime\\core\\public\\windows\\allowwindowsplatformtypes.h",
            "c:\\workspace\\sideproject1\\engine\\source\\runtime\\core\\public\\windows\\allowwindowsplatformatomics.h",
            "c:\\workspace\\sideproject1\\engine\\source\\runtime\\core\\public\\windows\\hidewindowsplatformatomics.h",
            "c:\\workspace\\sideproject1\\engine\\source\\runtime\\core\\public\\windows\\hidewindowsplatformtypes.h",
            "c:\\workspace\\sideproject1\\engine\\source\\runtime\\webbrowser\\private\\cef\\cefschemehandler.h",
            "c:\\workspace\\sideproject1\\engine\\source\\runtime\\webbrowser\\public\\iwebbrowserschemehandler.h",
            "c:\\workspace\\sideproject1\\engine\\source\\runtime\\webbrowser\\private\\cef\\cefresourcecontexthandler.h",
            "c:\\workspace\\sideproject1\\engine\\source\\runtime\\webbrowser\\private\\cef\\cefbrowserpopupfeatures.h",
            "c:\\workspace\\sideproject1\\engine\\source\\runtime\\webbrowser\\public\\iwebbrowserpopupfeatures.h",
            "c:\\workspace\\sideproject1\\engine\\source\\runtime\\core\\public\\windows\\allowwindowsplatformtypes.h",
            "c:\\workspace\\sideproject1\\engine\\source\\runtime\\core\\public\\windows\\allowwindowsplatformatomics.h",
            "c:\\workspace\\sideproject1\\engine\\source\\runtime\\core\\public\\windows\\hidewindowsplatformatomics.h",
            "c:\\workspace\\sideproject1\\engine\\source\\runtime\\core\\public\\windows\\hidewindowsplatformtypes.h",
            "c:\\workspace\\sideproject1\\engine\\source\\runtime\\webbrowser\\private\\cef\\cefwebbrowserwindow.h",
            "c:\\workspace\\sideproject1\\engine\\source\\runtime\\core\\public\\hal\\threadingbase.h",
            "c:\\workspace\\sideproject1\\engine\\source\\runtime\\core\\public\\hal\\threadmanager.h",
            "c:\\workspace\\sideproject1\\engine\\source\\runtime\\core\\public\\misc\\singlethreadevent.h",
            "c:\\workspace\\sideproject1\\engine\\source\\runtime\\online\\http\\public\\platformhttp.h",
            "c:\\workspace\\sideproject1\\engine\\source\\runtime\\online\\http\\public\\windows\\windowsplatformhttp.h",
            "c:\\workspace\\sideproject1\\engine\\source\\runtime\\online\\http\\public\\genericplatform\\genericplatformhttp.h",
            "c:\\workspace\\sideproject1\\engine\\source\\runtime\\webbrowser\\private\\cef\\cefbrowserpopupfeatures.cpp",
            "c:\\workspace\\sideproject1\\engine\\source\\runtime\\webbrowser\\private\\cef\\cefcookiemanager.cpp",
            "c:\\workspace\\sideproject1\\engine\\source\\runtime\\webbrowser\\public\\iwebbrowsercookiemanager.h",
            "c:\\workspace\\sideproject1\\engine\\source\\runtime\\webbrowser\\private\\cef\\cefimehandler.cpp",
            "c:\\workspace\\sideproject1\\engine\\source\\runtime\\webbrowser\\private\\cef\\cefimehandler.h",
            "c:\\workspace\\sideproject1\\engine\\source\\runtime\\core\\public\\windows\\allowwindowsplatformtypes.h",
            "c:\\workspace\\sideproject1\\engine\\source\\runtime\\core\\public\\windows\\allowwindowsplatformatomics.h",
            "c:\\workspace\\sideproject1\\engine\\source\\runtime\\core\\public\\windows\\hidewindowsplatformatomics.h",
            "c:\\workspace\\sideproject1\\engine\\source\\runtime\\core\\public\\windows\\hidewindowsplatformtypes.h",
            "c:\\workspace\\sideproject1\\engine\\source\\runtime\\webbrowser\\private\\cef\\ceftextinputmethodcontext.h",
            "c:\\workspace\\sideproject1\\engine\\source\\runtime\\core\\public\\windows\\allowwindowsplatformtypes.h",
            "c:\\workspace\\sideproject1\\engine\\source\\runtime\\core\\public\\windows\\allowwindowsplatformatomics.h",
            "c:\\workspace\\sideproject1\\engine\\source\\runtime\\core\\public\\windows\\hidewindowsplatformatomics.h",
            "c:\\workspace\\sideproject1\\engine\\source\\runtime\\core\\public\\windows\\hidewindowsplatformtypes.h",
            "c:\\workspace\\sideproject1\\engine\\source\\runtime\\applicationcore\\public\\genericplatform\\itextinputmethodsystem.h",
            "c:\\workspace\\sideproject1\\engine\\source\\runtime\\webbrowser\\private\\cef\\cefjsscripting.cpp",
            "c:\\workspace\\sideproject1\\engine\\source\\runtime\\webbrowser\\private\\cef\\cefjsscripting.h",
            "c:\\workspace\\sideproject1\\engine\\source\\runtime\\webbrowser\\public\\webjsfunction.h",
            "c:\\workspace\\sideproject1\\engine\\intermediate\\build\\win64\\unrealeditor\\inc\\webbrowser\\uht\\webjsfunction.generated.h",
            "c:\\workspace\\sideproject1\\engine\\source\\runtime\\webbrowser\\private\\webjsscripting.h",
            "c:\\workspace\\sideproject1\\engine\\source\\runtime\\core\\public\\windows\\allowwindowsplatformtypes.h",
            "c:\\workspace\\sideproject1\\engine\\source\\runtime\\core\\public\\windows\\allowwindowsplatformatomics.h",
            "c:\\workspace\\sideproject1\\engine\\source\\runtime\\core\\public\\windows\\hidewindowsplatformatomics.h",
            "c:\\workspace\\sideproject1\\engine\\source\\runtime\\core\\public\\windows\\hidewindowsplatformtypes.h",
            "c:\\workspace\\sideproject1\\engine\\source\\runtime\\webbrowser\\private\\cef\\cefjsstructserializerbackend.h",
            "c:\\workspace\\sideproject1\\engine\\source\\runtime\\serialization\\public\\istructserializerbackend.h",
            "c:\\workspace\\sideproject1\\engine\\source\\runtime\\core\\public\\windows\\allowwindowsplatformtypes.h",
            "c:\\workspace\\sideproject1\\engine\\source\\runtime\\core\\public\\windows\\hidewindowsplatformtypes.h",
            "c:\\workspace\\sideproject1\\engine\\source\\runtime\\webbrowser\\private\\cef\\cefjsstructdeserializerbackend.h",
            "c:\\workspace\\sideproject1\\engine\\source\\runtime\\serialization\\public\\istructdeserializerbackend.h",
            "c:\\workspace\\sideproject1\\engine\\source\\runtime\\core\\public\\windows\\allowwindowsplatformtypes.h",
            "c:\\workspace\\sideproject1\\engine\\source\\runtime\\core\\public\\windows\\allowwindowsplatformatomics.h",
            "c:\\workspace\\sideproject1\\engine\\source\\runtime\\core\\public\\windows\\hidewindowsplatformatomics.h",
            "c:\\workspace\\sideproject1\\engine\\source\\runtime\\core\\public\\windows\\hidewindowsplatformtypes.h",
            "c:\\workspace\\sideproject1\\engine\\source\\runtime\\serialization\\public\\structserializer.h",
            "c:\\workspace\\sideproject1\\engine\\source\\runtime\\serialization\\public\\structdeserializer.h",
            "c:\\workspace\\sideproject1\\engine\\source\\runtime\\webbrowser\\private\\cef\\cefjsstructdeserializerbackend.cpp",
            "c:\\workspace\\sideproject1\\engine\\source\\runtime\\webbrowser\\private\\cef\\cefjsstructserializerbackend.cpp",
            "c:\\workspace\\sideproject1\\engine\\source\\runtime\\webbrowser\\private\\cef\\cefresourcecontexthandler.cpp",
            "c:\\workspace\\sideproject1\\engine\\source\\runtime\\webbrowser\\private\\cef\\cefschemehandler.cpp",
            "c:\\workspace\\sideproject1\\engine\\source\\runtime\\webbrowser\\private\\cef\\ceftextinputmethodcontext.cpp",
            "c:\\workspace\\sideproject1\\engine\\source\\runtime\\webbrowser\\private\\cef\\cefwebbrowserwindow.cpp",
            "c:\\workspace\\sideproject1\\engine\\source\\runtime\\webbrowser\\public\\iwebbrowserdialog.h",
            "c:\\workspace\\sideproject1\\engine\\source\\runtime\\slatecore\\public\\textures\\slateupdatabletexture.h",
            "c:\\workspace\\sideproject1\\engine\\source\\runtime\\webbrowser\\private\\cef\\cefwebbrowserdialog.h",
            "c:\\workspace\\sideproject1\\engine\\source\\runtime\\core\\public\\windows\\allowwindowsplatformtypes.h",
            "c:\\workspace\\sideproject1\\engine\\source\\runtime\\core\\public\\windows\\hidewindowsplatformtypes.h",
            "c:\\workspace\\sideproject1\\engine\\source\\runtime\\webbrowser\\private\\cef\\cefwebbrowserwindowrhihelper.h",
            "c:\\workspace\\sideproject1\\engine\\source\\runtime\\cef3utils\\public\\cef3utils.h",
            "c:\\workspace\\sideproject1\\engine\\source\\runtime\\applicationcore\\public\\windows\\windowscursor.h",
            "c:\\workspace\\sideproject1\\engine\\source\\runtime\\webbrowser\\private\\cef\\cefwebbrowserwindowrhihelper.cpp",
            "c:\\workspace\\sideproject1\\engine\\source\\runtime\\engine\\public\\slate\\slatetextures.h",
            "c:\\workspace\\sideproject1\\engine\\source\\runtime\\core\\public\\windows\\allowwindowsplatformtypes.h",
            "c:\\program files (x86)\\windows kits\\10\\include\\10.0.19041.0\\um\\d3d11.h",
            "c:\\program files (x86)\\windows kits\\10\\include\\10.0.19041.0\\shared\\rpc.h",
            "c:\\program files (x86)\\windows kits\\10\\include\\10.0.19041.0\\shared\\pshpack8.h",
            "c:\\program files (x86)\\windows kits\\10\\include\\10.0.19041.0\\shared\\rpcdce.h",
            "c:\\program files (x86)\\windows kits\\10\\include\\10.0.19041.0\\shared\\rpcdcep.h",
            "c:\\program files (x86)\\windows kits\\10\\include\\10.0.19041.0\\um\\rpcnsi.h",
            "c:\\program files (x86)\\windows kits\\10\\include\\10.0.19041.0\\shared\\rpcnterr.h",
            "c:\\program files (x86)\\windows kits\\10\\include\\10.0.19041.0\\shared\\rpcasync.h",
            "c:\\program files (x86)\\windows kits\\10\\include\\10.0.19041.0\\shared\\pshpack8.h",
            "c:\\program files (x86)\\windows kits\\10\\include\\10.0.19041.0\\shared\\poppack.h",
            "c:\\program files (x86)\\windows kits\\10\\include\\10.0.19041.0\\shared\\poppack.h",
            "c:\\program files (x86)\\windows kits\\10\\include\\10.0.19041.0\\shared\\rpcndr.h",
            "c:\\program files (x86)\\windows kits\\10\\include\\10.0.19041.0\\shared\\pshpack8.h",
            "c:\\program files (x86)\\windows kits\\10\\include\\10.0.19041.0\\um\\rpcnsip.h",
            "c:\\program files (x86)\\windows kits\\10\\include\\10.0.19041.0\\shared\\rpcsal.h",
            "c:\\program files (x86)\\windows kits\\10\\include\\10.0.19041.0\\shared\\poppack.h",
            "c:\\program files (x86)\\windows kits\\10\\include\\10.0.19041.0\\um\\ole2.h",
            "c:\\program files (x86)\\windows kits\\10\\include\\10.0.19041.0\\shared\\pshpack8.h",
            "c:\\program files (x86)\\windows kits\\10\\include\\10.0.19041.0\\um\\objbase.h",
            "c:\\program files (x86)\\windows kits\\10\\include\\10.0.19041.0\\shared\\pshpack8.h",
            "c:\\program files (x86)\\windows kits\\10\\include\\10.0.19041.0\\um\\combaseapi.h",
            "c:\\program files (x86)\\windows kits\\10\\include\\10.0.19041.0\\shared\\pshpack8.h",
            "c:\\program files (x86)\\windows kits\\10\\include\\10.0.19041.0\\shared\\wtypesbase.h",
            "c:\\program files (x86)\\windows kits\\10\\include\\10.0.19041.0\\shared\\guiddef.h",
            "c:\\program files (x86)\\windows kits\\10\\include\\10.0.19041.0\\um\\unknwnbase.h",
            "c:\\program files (x86)\\windows kits\\10\\include\\10.0.19041.0\\um\\objidlbase.h",
            "c:\\program files (x86)\\windows kits\\10\\include\\10.0.19041.0\\shared\\guiddef.h",
            "c:\\program files (x86)\\windows kits\\10\\include\\10.0.19041.0\\um\\cguid.h",
            "c:\\program files (x86)\\windows kits\\10\\include\\10.0.19041.0\\shared\\poppack.h",
            "c:\\program files (x86)\\windows kits\\10\\include\\10.0.19041.0\\um\\coml2api.h",
            "c:\\program files (x86)\\windows kits\\10\\include\\10.0.19041.0\\um\\objidl.h",
            "c:\\program files (x86)\\windows kits\\10\\include\\10.0.19041.0\\um\\unknwn.h",
            "c:\\program files (x86)\\windows kits\\10\\include\\10.0.19041.0\\shared\\wtypes.h",
            "c:\\program files (x86)\\windows kits\\10\\include\\10.0.19041.0\\um\\propidlbase.h",
            "c:\\program files (x86)\\windows kits\\10\\include\\10.0.19041.0\\um\\oaidl.h",
            "c:\\program files (x86)\\windows kits\\10\\include\\10.0.19041.0\\um\\urlmon.h",
            "c:\\program files (x86)\\windows kits\\10\\include\\10.0.19041.0\\um\\oleidl.h",
            "c:\\program files (x86)\\windows kits\\10\\include\\10.0.19041.0\\um\\servprov.h",
            "c:\\program files (x86)\\windows kits\\10\\include\\10.0.19041.0\\um\\msxml.h",
            "c:\\program files (x86)\\windows kits\\10\\include\\10.0.19041.0\\um\\propidl.h",
            "c:\\program files (x86)\\windows kits\\10\\include\\10.0.19041.0\\shared\\poppack.h",
            "c:\\program files (x86)\\windows kits\\10\\include\\10.0.19041.0\\um\\oleauto.h",
            "c:\\program files (x86)\\windows kits\\10\\include\\10.0.19041.0\\shared\\pshpack8.h",
            "c:\\program files (x86)\\windows kits\\10\\include\\10.0.19041.0\\shared\\poppack.h",
            "c:\\program files (x86)\\windows kits\\10\\include\\10.0.19041.0\\shared\\poppack.h",
            "c:\\program files (x86)\\windows kits\\10\\include\\10.0.19041.0\\um\\ocidl.h",
            "c:\\program files (x86)\\windows kits\\10\\include\\10.0.19041.0\\shared\\dxgi.h",
            "c:\\program files (x86)\\windows kits\\10\\include\\10.0.19041.0\\shared\\dxgicommon.h",
            "c:\\program files (x86)\\windows kits\\10\\include\\10.0.19041.0\\shared\\dxgitype.h",
            "c:\\program files (x86)\\windows kits\\10\\include\\10.0.19041.0\\shared\\dxgiformat.h",
            "c:\\program files (x86)\\windows kits\\10\\include\\10.0.19041.0\\um\\d3dcommon.h",
            "c:\\program files (x86)\\windows kits\\10\\include\\10.0.19041.0\\um\\d3d11sdklayers.h",
            "c:\\program files (x86)\\windows kits\\10\\include\\10.0.19041.0\\um\\d3d10_1.h",
            "c:\\program files (x86)\\windows kits\\10\\include\\10.0.19041.0\\um\\d3d10.h",
            "c:\\program files (x86)\\windows kits\\10\\include\\10.0.19041.0\\um\\d3d10sdklayers.h",
            "c:\\program files (x86)\\windows kits\\10\\include\\10.0.19041.0\\um\\d3d10misc.h",
            "c:\\program files (x86)\\windows kits\\10\\include\\10.0.19041.0\\um\\d3d10shader.h",
            "c:\\program files (x86)\\windows kits\\10\\include\\10.0.19041.0\\um\\d3d10effect.h",
            "c:\\program files (x86)\\windows kits\\10\\include\\10.0.19041.0\\um\\d3d10_1shader.h",
            "c:\\program files (x86)\\windows kits\\10\\include\\10.0.19041.0\\um\\d3d11_1.h",
            "c:\\program files (x86)\\windows kits\\10\\include\\10.0.19041.0\\shared\\dxgi1_2.h",
            "c:\\workspace\\sideproject1\\engine\\source\\runtime\\core\\public\\windows\\hidewindowsplatformtypes.h",
            "c:\\workspace\\sideproject1\\engine\\source\\runtime\\webbrowser\\private\\mobilejs\\mobilejsscripting.cpp",
            "c:\\workspace\\sideproject1\\engine\\source\\runtime\\webbrowser\\private\\mobilejs\\mobilejsscripting.h",
            "c:\\workspace\\sideproject1\\engine\\source\\runtime\\webbrowser\\private\\mobilejs\\mobilejsstructdeserializerbackend.cpp",
            "c:\\workspace\\sideproject1\\engine\\source\\runtime\\webbrowser\\private\\mobilejs\\mobilejsstructdeserializerbackend.h",
            "c:\\workspace\\sideproject1\\engine\\source\\runtime\\webbrowser\\private\\mobilejs\\mobilejsstructserializerbackend.cpp",
            "c:\\workspace\\sideproject1\\engine\\source\\runtime\\webbrowser\\private\\mobilejs\\mobilejsstructserializerbackend.h",
            "c:\\workspace\\sideproject1\\engine\\source\\runtime\\webbrowser\\private\\native\\nativejsscripting.cpp",
            "c:\\workspace\\sideproject1\\engine\\source\\runtime\\webbrowser\\private\\native\\nativejsscripting.h",
            "c:\\workspace\\sideproject1\\engine\\source\\runtime\\webbrowser\\private\\native\\nativejsstructserializerbackend.h",
            "c:\\workspace\\sideproject1\\engine\\source\\runtime\\serialization\\public\\backends\\jsonstructserializerbackend.h",
            "c:\\workspace\\sideproject1\\engine\\source\\runtime\\webbrowser\\private\\native\\nativejsstructdeserializerbackend.h",
            "c:\\workspace\\sideproject1\\engine\\source\\runtime\\serialization\\public\\backends\\jsonstructdeserializerbackend.h",
            "c:\\workspace\\sideproject1\\engine\\source\\runtime\\webbrowser\\private\\native\\nativewebbrowserproxy.h",
            "c:\\workspace\\sideproject1\\engine\\source\\runtime\\webbrowser\\private\\native\\nativejsstructdeserializerbackend.cpp",
            "c:\\workspace\\sideproject1\\engine\\source\\runtime\\webbrowser\\private\\native\\nativejsstructserializerbackend.cpp",
            "c:\\workspace\\sideproject1\\engine\\source\\runtime\\webbrowser\\private\\native\\nativewebbrowserproxy.cpp",
            "c:\\workspace\\sideproject1\\engine\\source\\runtime\\core\\public\\misc\\embeddedcommunication.h",
            "c:\\workspace\\sideproject1\\engine\\source\\runtime\\webbrowser\\private\\swebbrowser.cpp",
            "c:\\workspace\\sideproject1\\engine\\source\\runtime\\slate\\public\\widgets\\input\\seditabletextbox.h",
            "c:\\workspace\\sideproject1\\engine\\source\\runtime\\slate\\public\\widgets\\input\\seditabletext.h",
            "c:\\workspace\\sideproject1\\engine\\source\\runtime\\slate\\public\\widgets\\text\\islateeditabletextwidget.h",
            "c:\\workspace\\sideproject1\\engine\\intermediate\\build\\win64\\unrealeditor\\inc\\slate\\uht\\islateeditabletextwidget.generated.h",
            "c:\\workspace\\sideproject1\\engine\\source\\runtime\\slate\\public\\widgets\\images\\sthrobber.h",
            "c:\\workspace\\sideproject1\\engine\\source\\runtime\\webbrowser\\private\\swebbrowserview.cpp",
            "c:\\workspace\\sideproject1\\engine\\source\\runtime\\webbrowser\\public\\webbrowserviewport.h",
            "c:\\workspace\\sideproject1\\engine\\source\\runtime\\webbrowser\\public\\iwebbrowseradapter.h",
            "c:\\workspace\\sideproject1\\engine\\source\\runtime\\webbrowser\\private\\webbrowseradapter.cpp",
            "c:\\workspace\\sideproject1\\engine\\source\\runtime\\webbrowser\\private\\webbrowsermodule.cpp",
            "c:\\workspace\\sideproject1\\engine\\source\\runtime\\webbrowser\\private\\webbrowsersingleton.cpp",
            "c:\\workspace\\sideproject1\\engine\\source\\runtime\\core\\public\\internationalization\\culture.h",
            "c:\\workspace\\sideproject1\\engine\\source\\runtime\\core\\public\\windows\\allowwindowsplatformtypes.h",
            "c:\\workspace\\sideproject1\\engine\\source\\thirdparty\\cef3\\cef_binary_90.6.7+g19ba721+chromium-90.0.4430.212_windows64\\include\\cef_version.h",
            "c:\\workspace\\sideproject1\\engine\\source\\runtime\\core\\public\\windows\\hidewindowsplatformtypes.h",
            "c:\\workspace\\sideproject1\\engine\\source\\runtime\\webbrowser\\private\\webbrowserviewport.cpp",
            "c:\\workspace\\sideproject1\\engine\\source\\runtime\\webbrowser\\private\\webjsfunction.cpp",
            "c:\\workspace\\sideproject1\\engine\\intermediate\\build\\win64\\unrealeditor\\inc\\webbrowser\\uht\\webjsfunction.gen.cpp",
            "c:\\workspace\\sideproject1\\engine\\source\\runtime\\core\\public\\windows\\allowwindowsplatformtypes.h",
            "c:\\workspace\\sideproject1\\engine\\source\\runtime\\core\\public\\windows\\allowwindowsplatformatomics.h",
            "c:\\workspace\\sideproject1\\engine\\source\\runtime\\core\\public\\windows\\hidewindowsplatformatomics.h",
            "c:\\workspace\\sideproject1\\engine\\source\\runtime\\core\\public\\windows\\hidewindowsplatformtypes.h"
        ],
        "ImportedModules": [],
        "ImportedHeaderUnits": []
    }
}